{
    "menu": [
        {
            "class": "icon-hangzhengquhua",
            "show": true,
            "title": "行政区划",
            "showeyes":true,
            "data": [
                {
                    "tit": "福州市",
                    "show": true,
                    "status": false,
                    "isLeaf": false,
                    "lists": []
                }
            ]
        },
        {
            "class": "icon-kongjianxinxi",
            "show": false,
            "showeyes":true,
            "title": "空间信息",
            "data": [
                {
                    "tit": "部件信息",
                    "show": true,
                    "status": true,
                    "isLeaf": false,
                    "lists": [
                        {
                            "tit": "地形",
                            "show": true,
                            "isLeaf": true
                        },
                        {
                            "tit": "建筑物",
                            "show": true,
                            "isLeaf": true,
                            "lists": [
                                "buildingA05JZ019",
                                "buildingbuilding"
                            ]
                        },
                        {
                            "tit": "植被",
                            "show": true,
                            "isLeaf": true,
                            "lists": [
                                "buildingtree"
                            ]
                        },
                        {
                            "tit": "场地",
                            "show": true,
                            "isLeaf": true,
                            "lists": [
                                "buildingdimian"
                            ]
                        },
                        {
                            "tit": "城市部件",
                            "show": true,
                            "isLeaf": true,
                            "lists": [
                                "buildinghp",
                                "buildingpingshanshequ"
                            ]
                        }
                    ]
                }
            ]
        },
        {
            "class": "icon-gonggongxinxi",
            "show": false,
            "title": "管线信息",
            "showeyes":true,
            
            "data": [
                {
                    "tit": "管线",
                    "show": true,
                    "status": true,
                    "isLeaf": false,
                    "lists": [
                        {
                            "tit": "铁通管线",
                            "show": true,
                            "isLeaf": true
                        },
                        {
                            "tit": "雨水管点",
                            "show": true,
                            "isLeaf": true
                        },
                        {
                            "tit": "军用通讯管点",
                            "show": true,
                            "isLeaf": true
                        },
                        {
                            "tit": "讯通管点",
                            "show": true,
                            "isLeaf": true
                        },
                        {
                            "tit": "温泉管点",
                            "show": true,
                            "isLeaf": true
                        },
                        {
                            "tit": "天然气管线",
                            "show": true,
                            "isLeaf": true
                        },
                        {
                            "tit": "电信管点",
                            "show": true,
                            "isLeaf": true
                        },
                        {
                            "tit": "移动管线",
                            "show": true,
                            "isLeaf": true
                        },
                        {
                            "tit": "给水管线",
                            "show": true,
                            "isLeaf": true
                        },
                        {
                            "tit": "石油管点",
                            "show": true,
                            "isLeaf": true
                        },
                        {
                            "tit": "联通管线",
                            "show": true,
                            "isLeaf": true
                        },
                        {
                            "tit": "石油管线",
                            "show": true,
                            "isLeaf": true
                        },
                        {
                            "tit": "污水管线",
                            "show": true,
                            "isLeaf": true
                        },
                        {
                            "tit": "讯通管线",
                            "show": true,
                            "isLeaf": true
                        },
                        {
                            "tit": "天然气管点",
                            "show": true,
                            "isLeaf": true
                        },
                        {
                            "tit": "温泉管线",
                            "show": true,
                            "isLeaf": true
                        },
                        {
                            "tit": "电信管线",
                            "show": true,
                            "isLeaf": true
                        },
                        {
                            "tit": "铁通管点",
                            "show": true,
                            "isLeaf": true
                        },
                        {
                            "tit": "交通信号管线",
                            "show": true,
                            "isLeaf": true
                        },
                        {
                            "tit": "移动管点",
                            "show": true,
                            "isLeaf": true
                        },
                        {
                            "tit": "路灯管线",
                            "show": true,
                            "isLeaf": true
                        },
                        {
                            "tit": "给水管点",
                            "show": true,
                            "isLeaf": true
                        },
                        {
                            "tit": "网通管线",
                            "show": true,
                            "isLeaf": true
                        },
                        {
                            "tit": "路灯管点",
                            "show": true,
                            "isLeaf": true
                        },
                        {
                            "tit": "联通管点",
                            "show": true,
                            "isLeaf": true
                        },
                        {
                            "tit": "雨水管线",
                            "show": true,
                            "isLeaf": true
                        },
                        {
                            "tit": "污水管点",
                            "show": true,
                            "isLeaf": true
                        },
                        {
                            "tit": "军用通讯管线",
                            "show": true,
                            "isLeaf": true
                        },
                        {
                            "tit": "交通信号管点",
                            "show": true,
                            "isLeaf": true
                        },
                        {
                            "tit": "网通管点",
                            "show": true,
                            "isLeaf": true
                        }
                    ]
                }
            ]
        }
    ]
}